Metadata-Version: 2.1
Name: tablemaster
Version: 1.2.12
Summary: A Python package makes it easy to manage tables anywhere
Home-page: https://github.com/ilivid/tablemaster
Author: Livid
Author-email: livid.su@gmail.com
License-File: LICENSE
Requires-Dist: PyMySQL
Requires-Dist: SQLAlchemy
Requires-Dist: pandas
Requires-Dist: python-dateutil
Requires-Dist: gspread
Requires-Dist: tqdm
Requires-Dist: numpy
Requires-Dist: pyyaml
Requires-Dist: openpyxl
